tvsd/.gitignore
tvsd/__init__.py
tvsd/__main__.py
tvsd/actions.py
tvsd/cli.py
tvsd/config.py
tvsd/download.py
tvsd/search.py
tvsd/sources/__init__.py
tvsd/sources/_bu_ding_3.py
tvsd/sources/_ify.py
tvsd/sources/_mov.py
tvsd/sources/_template.py
tvsd/sources/_ying_hua.py
tvsd/sources/base.py
tvsd/sources/olevod.py
tvsd/sources/ssstv.py
tvsd/sources/xiao_bao.py
tvsd/types/__init__.py
tvsd/types/episode.py
tvsd/types/season.py
tvsd/types/show.py
tvsd/utils.py
tvsd-1.4.1.dist-info/LICENSE
tvsd-1.4.1.dist-info/METADATA
tvsd-1.4.1.dist-info/WHEEL
tvsd-1.4.1.dist-info/entry_points.txt
tvsd-1.4.1.dist-info/RECORD
