Metadata-Version: 2.1
Name: tvsd
Version: 1.4.1
Summary: search and downloads TV and movies from websites
Home-page: https://github.com/sheepyy039/TVSD.git
License: MIT
Keywords: download,tv,search,m3u8
Author: JYYYeung
Author-email: yeungjyy@gmail.com
Requires-Python: >=3.10,<4.0
Classifier: Development Status :: 5 - Production/Stable
Classifier: Environment :: Console
Classifier: License :: OSI Approved :: MIT License
Classifier: Programming Language :: Python :: 3
Classifier: Programming Language :: Python :: 3.10
Classifier: Programming Language :: Python :: 3.11
Classifier: Programming Language :: Python :: 3.12
Classifier: Topic :: Utilities
Requires-Dist: beautifulsoup4 (>=4.12.2,<5.0.0)
Requires-Dist: chinese-converter (>=1.1.1,<2.0.0)
Requires-Dist: cloudscraper (>=1.2.71,<2.0.0)
Requires-Dist: crispy-bulma (>=0.11.0,<0.12.0)
Requires-Dist: django (>=5.0.2,<6.0.0)
Requires-Dist: django-crispy-forms (>=2.1,<3.0)
Requires-Dist: django-simple-bulma (>=2.6.0,<3.0.0)
Requires-Dist: django-unicorn (>=0.59.0,<0.60.0)
Requires-Dist: docstring-parser (>=0.15,<0.16)
Requires-Dist: dynaconf (>=3.2.4,<4.0.0)
Requires-Dist: m3u8-To-MP4 (>=0.1.11,<0.2.0)
Requires-Dist: multipledispatch (>=1.0.0,<2.0.0)
Requires-Dist: pathvalidate (>=3.2.0,<4.0.0)
Requires-Dist: poetry-plugin-export (>=1.8.0,<2.0.0)
Requires-Dist: pytest (>=7.4.2,<8.0.0)
Requires-Dist: rich (>=13.6.0,<14.0.0)
Requires-Dist: typer (>=0.9.0,<0.10.0)
Requires-Dist: whitenoise (>=6.6.0,<7.0.0)
Project-URL: Changelog, https://github.com/sheepyy039/TVSD/blob/main/CHANGELOG.md
Project-URL: Documentation, https://sheepyy039.github.io/TVSD
Project-URL: Repository, https://github.com/sheepyy039/TVSD.git
